zwcef/__init__.py
zwcef/__version__.py
zwcef-0.0.1.dist-info/METADATA
zwcef-0.0.1.dist-info/WHEEL
zwcef-0.0.1.dist-info/top_level.txt
zwcef-0.0.1.dist-info/RECORD
